gym_evn/__init__.py
gym_evn/envs/__init__.py
gym_evn/envs/gym_env.py
gym_evn-0.0.1.dist-info/METADATA
gym_evn-0.0.1.dist-info/WHEEL
gym_evn-0.0.1.dist-info/top_level.txt
gym_evn-0.0.1.dist-info/RECORD
